orquestra/sdk/__init__.py
orquestra/sdk/exceptions.py
orquestra/sdk/py.typed
orquestra/sdk/_client/__init__.py
orquestra/sdk/_client/_base/__init__.py
orquestra/sdk/_client/_base/_ast.py
orquestra/sdk/_client/_base/_docker_images.py
orquestra/sdk/_client/_base/_dsl.py
orquestra/sdk/_client/_base/_env.py
orquestra/sdk/_client/_base/_factory.py
orquestra/sdk/_client/_base/_in_process_runtime.py
orquestra/sdk/_client/_base/_jwt.py
orquestra/sdk/_client/_base/_services.py
orquestra/sdk/_client/_base/_traversal.py
orquestra/sdk/_client/_base/_viz.py
orquestra/sdk/_client/_base/_workflow.py
orquestra/sdk/_client/_base/loader.py
orquestra/sdk/_client/_base/_api/__init__.py
orquestra/sdk/_client/_base/_api/_task_run.py
orquestra/sdk/_client/_base/_api/_wf_run.py
orquestra/sdk/_client/_base/_config/__init__.py
orquestra/sdk/_client/_base/_config/_api.py
orquestra/sdk/_client/_base/_config/_fs.py
orquestra/sdk/_client/_base/_config/_settings.py
orquestra/sdk/_client/_base/_driver/__init__.py
orquestra/sdk/_client/_base/_driver/_ce_runtime.py
orquestra/sdk/_client/_base/_driver/_client.py
orquestra/sdk/_client/_base/_driver/_exceptions.py
orquestra/sdk/_client/_base/_driver/_models.py
orquestra/sdk/_client/_base/_spaces/__init__.py
orquestra/sdk/_client/_base/_spaces/_api.py
orquestra/sdk/_client/_base/_spaces/_resolver.py
orquestra/sdk/_client/_base/_testing/__init__.py
orquestra/sdk/_client/_base/_testing/_example_wfs.py
orquestra/sdk/_client/_base/_testing/_ipc.py
orquestra/sdk/_client/_base/_testing/_long_import.py
orquestra/sdk/_client/_base/_testing/_reloaders.py
orquestra/sdk/_client/_base/_testing/resp_mocks.py
orquestra/sdk/_client/_base/_testing/data/get_task_logs_response/logs.tar.gz
orquestra/sdk/_client/_base/_testing/data/get_wf_logs_response/logs.tar.gz
orquestra/sdk/_client/_base/_testing/data/get_wf_system_logs_response/sys_logs.tar.gz
orquestra/sdk/_client/_base/cli/_arg_resolvers.py
orquestra/sdk/_client/_base/cli/_cli_logs.py
orquestra_sdk-1.1.0.dist-info/METADATA
orquestra_sdk-1.1.0.dist-info/WHEEL
orquestra_sdk-1.1.0.dist-info/entry_points.txt
orquestra_sdk-1.1.0.dist-info/licenses/LICENSE
orquestra_sdk-1.1.0.dist-info/RECORD
