Metadata-Version: 2.3
Name: orquestra-sdk
Version: 1.1.0
Summary: Compose Orquestra workflows using a Python DSL
Project-URL: Homepage, https://github.com/zapata-engineering/orquestra-sdk
Project-URL: Documentation, https://docs.orquestra.io
Project-URL: Repository, https://github.com/zapata-engineering/orquestra-sdk.git
Project-URL: Issues, https://github.com/zapata-engineering/orquestra-sdk/issues
Author-email: "Zapata Computing Inc." <info@zapatacomputing.com>
License:                                  Apache License
License-File: LICENSE
Classifier: License :: OSI Approved :: Apache Software License
Classifier: Operating System :: OS Independent
Classifier: Programming Language :: Python :: 3
Classifier: Topic :: Scientific/Engineering
Requires-Python: >=3.8
Requires-Dist: aiohttp>=3.9.0
Requires-Dist: argcomplete
Requires-Dist: click!=8.1.4,>=8.0
Requires-Dist: cloudpickle==2.2.1
Requires-Dist: cloup>=2.0
Requires-Dist: dill==0.3.6
Requires-Dist: filelock>=3.3.2
Requires-Dist: gitpython
Requires-Dist: graphviz
Requires-Dist: importlib-metadata>=4.0
Requires-Dist: inquirer>=3.0
Requires-Dist: orquestra-workflow-shared~=2.0.0
Requires-Dist: packaging>=21
Requires-Dist: pandas>=1.4
Requires-Dist: pip-api>=0.0.30
Requires-Dist: pydantic>1.10.7
Requires-Dist: pyjwt>=2.6
Requires-Dist: requests>=2.28
Requires-Dist: rich>=13.5
Requires-Dist: tabulate
Requires-Dist: typing-extensions>=4.1.0
Requires-Dist: wrapt
Requires-Dist: wurlitzer>=3.0
Provides-Extra: all
Requires-Dist: orquestra-workflow-runtime[dashboard]~=2.0.0; extra == 'all'
Provides-Extra: dashboard
Requires-Dist: orquestra-workflow-runtime[dashboard]~=2.0.0; extra == 'dashboard'
Provides-Extra: dev
Requires-Dist: black~=23.7; extra == 'dev'
Requires-Dist: diff-cover; extra == 'dev'
Requires-Dist: flake8-pyproject>=1.2.3; extra == 'dev'
Requires-Dist: flake8>=4.0.0; extra == 'dev'
Requires-Dist: freezegun; extra == 'dev'
Requires-Dist: furo==2023.7.26; extra == 'dev'
Requires-Dist: isort~=5.9.0; extra == 'dev'
Requires-Dist: jinja2>=3.0.0; extra == 'dev'
Requires-Dist: mlflow-skinny; extra == 'dev'
Requires-Dist: mypy~=0.910; extra == 'dev'
Requires-Dist: numpy; extra == 'dev'
Requires-Dist: orquestra-workflow-runtime[dashboard]~=2.0.0; extra == 'dev'
Requires-Dist: pydoclint; extra == 'dev'
Requires-Dist: pymarkdownlnt; extra == 'dev'
Requires-Dist: pyright!=1.1.340,!=1.1.341; extra == 'dev'
Requires-Dist: pytest-cov>=2.12; extra == 'dev'
Requires-Dist: pytest-dependency; extra == 'dev'
Requires-Dist: pytest-httpserver; extra == 'dev'
Requires-Dist: pytest-timeout>=2.0.0; extra == 'dev'
Requires-Dist: pytest>=6.2; extra == 'dev'
Requires-Dist: responses!=0.24,>=0.20; extra == 'dev'
Requires-Dist: ruff>=0.2.0; extra == 'dev'
Requires-Dist: scikit-learn; extra == 'dev'
Requires-Dist: sphinx-autoapi==2.1.1; extra == 'dev'
Requires-Dist: sphinx-autobuild==2021.3.14; extra == 'dev'
Requires-Dist: sphinx-click==4.4.0; extra == 'dev'
Requires-Dist: sphinx-copybutton==0.5.2; extra == 'dev'
Requires-Dist: sphinx-design==0.4.1; extra == 'dev'
Requires-Dist: sphinx-togglebutton==0.3.2; extra == 'dev'
Requires-Dist: sphinx<7.0,>6.0; extra == 'dev'
Requires-Dist: sphinxcontrib-autoprogram==0.1.8; extra == 'dev'
Requires-Dist: sphinxcontrib-youtube==1.2.0; extra == 'dev'
Requires-Dist: sphinxemoji==0.2.0; extra == 'dev'
Requires-Dist: types-psutil; extra == 'dev'
Requires-Dist: types-pygments; extra == 'dev'
Requires-Dist: types-requests; extra == 'dev'
Requires-Dist: types-setuptools; extra == 'dev'
Requires-Dist: types-tabulate; extra == 'dev'
Provides-Extra: docs
Requires-Dist: furo==2023.7.26; extra == 'docs'
Requires-Dist: jinja2>=3.0.0; extra == 'docs'
Requires-Dist: sphinx-autoapi==2.1.1; extra == 'docs'
Requires-Dist: sphinx-autobuild==2021.3.14; extra == 'docs'
Requires-Dist: sphinx-click==4.4.0; extra == 'docs'
Requires-Dist: sphinx-copybutton==0.5.2; extra == 'docs'
Requires-Dist: sphinx-design==0.4.1; extra == 'docs'
Requires-Dist: sphinx-togglebutton==0.3.2; extra == 'docs'
Requires-Dist: sphinx<7.0,>6.0; extra == 'docs'
Requires-Dist: sphinxcontrib-autoprogram==0.1.8; extra == 'docs'
Requires-Dist: sphinxcontrib-youtube==1.2.0; extra == 'docs'
Requires-Dist: sphinxemoji==0.2.0; extra == 'docs'
Provides-Extra: ray
Requires-Dist: orquestra-workflow-runtime[ray]~=2.0.0; extra == 'ray'
